fastapi_mako.py
FastAPI_Mako-0.5.0.dist-info/LICENSE
FastAPI_Mako-0.5.0.dist-info/METADATA
FastAPI_Mako-0.5.0.dist-info/WHEEL
FastAPI_Mako-0.5.0.dist-info/top_level.txt
FastAPI_Mako-0.5.0.dist-info/RECORD
