Metadata-Version: 2.1
Name: FastAPI-Mako
Version: 0.5.0
Summary: Mako templating support for FastAPI.
Home-page: https://github.com/dongweiming/fastapi-mako
Author: LouisYoung
Author-email: yangzhikai2007@163.com
License: Apache 2
Platform: any
Classifier: Framework :: AsyncIO
Classifier: Environment :: Web Environment
Classifier: Intended Audience :: Developers
Classifier: License :: OSI Approved :: Apache Software License
Classifier: Operating System :: OS Independent
Classifier: Programming Language :: Python
Classifier: Programming Language :: Python :: 3
Classifier: Topic :: Internet :: WWW/HTTP :: Dynamic Content
Classifier: Topic :: Software Development :: Libraries :: Python Modules
Requires-Dist: starlette
Requires-Dist: Mako
